siberia/TSeriesClass.py
siberia/__init__.py
siberia-0.0.1.dist-info/licenses/LICENSE
siberia-0.0.1.dist-info/METADATA
siberia-0.0.1.dist-info/WHEEL
siberia-0.0.1.dist-info/top_level.txt
siberia-0.0.1.dist-info/RECORD
