Metadata-Version: 2.4
Name: siberia
Version: 0.0.1
Summary: SIBERIA (SIgned BEnchmarks foR tIme series Analysis) provides maximum-entropy null models and validation methods for signed networks derived from time series.
Author-email: Marzio Di Vece <marzio.divece@sns.it>, Emanuele Agrimi <emanuele.agrimi@imtlucca.it>, Samuele Tatullo <samuele.tatullo@imtlucca.it>
Project-URL: Homepage, https://github.com/MarsMDK/siberia
Keywords: maximum entropy methods,time series,network filtering,graph,network,entropy
Classifier: License :: OSI Approved :: GNU General Public License v3 (GPLv3)
Classifier: Programming Language :: Python :: 3.9
Classifier: Programming Language :: Python :: 3.10
Requires-Python: >=3.9
License-File: LICENSE
Requires-Dist: numpy
Requires-Dist: scipy
Requires-Dist: pandas
Requires-Dist: matplotlib
Requires-Dist: tqdm
Requires-Dist: joblib
Requires-Dist: numba
Requires-Dist: statsmodels
Requires-Dist: fast-poibin
Requires-Dist: seaborn
Provides-Extra: dev
Requires-Dist: pytest; extra == "dev"
Dynamic: license-file
